ethics_dashboard_models-0.6.dist-info/licenses/LICENSE
models/__init__.py
models/answer.py
models/assignment.py
models/case_study.py
models/case_study_option.py
models/db.py
models/enrollment.py
models/feedback.py
models/form.py
models/form_description.py
models/grade.py
models/professor.py
models/question.py
models/school_class.py
models/slider_question.py
models/student.py
models/submission.py
models/ta.py
ethics_dashboard_models-0.6.dist-info/METADATA
ethics_dashboard_models-0.6.dist-info/WHEEL
ethics_dashboard_models-0.6.dist-info/top_level.txt
ethics_dashboard_models-0.6.dist-info/RECORD
